pytablewriter_altrow_theme/__init__.py
pytablewriter_altrow_theme/__version__.py
pytablewriter_altrow_theme/pugin.py
pytablewriter_altrow_theme-0.2.0.dist-info/LICENSE
pytablewriter_altrow_theme-0.2.0.dist-info/METADATA
pytablewriter_altrow_theme-0.2.0.dist-info/WHEEL
pytablewriter_altrow_theme-0.2.0.dist-info/top_level.txt
pytablewriter_altrow_theme-0.2.0.dist-info/RECORD
