Metadata-Version: 2.1
Name: pytablewriter-altrow-theme
Version: 0.2.0
Summary: A pytablewriter plugin to provide a theme that colored rows alternatively.
Home-page: https://github.com/thombashi/pytablewriter-altrow-theme
Author: Tsuyoshi Hombashi
Author-email: tsuyoshi.hombashi@gmail.com
License: MIT License
Project-URL: Changlog, https://github.com/thombashi/pytablewriter-altrow-theme/releases
Project-URL: Source, https://github.com/thombashi/pytablewriter-altrow-theme
Project-URL: Tracker, https://github.com/thombashi/pytablewriter-altrow-theme/issues
Keywords: pytablewriter,plugin,theme
Classifier: Development Status :: 4 - Beta
Classifier: Environment :: Plugins
Classifier: Intended Audience :: Developers
Classifier: Intended Audience :: Information Technology
Classifier: License :: OSI Approved :: MIT License
Classifier: Operating System :: OS Independent
Classifier: Programming Language :: Python :: 3
Classifier: Programming Language :: Python :: 3.7
Classifier: Programming Language :: Python :: 3.8
Classifier: Programming Language :: Python :: 3.9
Classifier: Programming Language :: Python :: 3.10
Classifier: Programming Language :: Python :: 3.11
Classifier: Programming Language :: Python :: 3 :: Only
Classifier: Programming Language :: Python :: Implementation :: CPython
Classifier: Programming Language :: Python :: Implementation :: PyPy
Classifier: Topic :: Software Development :: Libraries
Classifier: Topic :: Software Development :: Libraries :: Python Modules
Requires-Python: >=3.7
License-File: LICENSE
Requires-Dist: pytablewriter <2,>=0.59.0
Requires-Dist: tcolorpy <1,>=0.0.5
Provides-Extra: test
Requires-Dist: pytest >=6.0.1 ; extra == 'test'
Requires-Dist: pytest-discord >=0.1.4 ; extra == 'test'
